dianping.openapi.python.sdk-0.0.1.dist-info/DESCRIPTION.rst
dianping.openapi.python.sdk-0.0.1.dist-info/METADATA
dianping.openapi.python.sdk-0.0.1.dist-info/RECORD
dianping.openapi.python.sdk-0.0.1.dist-info/WHEEL
dianping.openapi.python.sdk-0.0.1.dist-info/metadata.json
dianping.openapi.python.sdk-0.0.1.dist-info/top_level.txt
dzopen/__init__.py
dzopen/client.py
dzopen/dzauth.py
dzopen/sign.py
dzopen/request/__init__.py
dzopen/request/book.py
dzopen/request/codepay.py
dzopen/request/merchantdata.py
dzopen/request/oauth.py
dzopen/request/poi.py
dzopen/request/tuangou.py
dzopen/request/ugc.py
dzopen/test/__init__.py
dzopen/test/book.py
dzopen/test/codepay.py
dzopen/test/merchantdata.py
dzopen/test/oauth.py
dzopen/test/poi.py
dzopen/test/tuangou.py
dzopen/test/ugc.py
