Metadata-Version: 2.0
Name: dianping.openapi.python.sdk
Version: 0.0.1
Summary: dianping openapi python sdk
Home-page: UNKNOWN
Author: Json
Author-email: zhangzhongbao02@meituan.com
License: MIT License
Keywords: dianping,openapi
Platform: UNKNOWN
